Metadata-Version: 2.1
Name: init-args-serializer
Version: 1.1
Summary: Python serializer based on init-args
Home-page: https://github.com/Xfel/init-args-serializer
Author: Felix Treede
Author-email: felixtreede@yahoo.de
License: UNKNOWN
Keywords: serialization,serializer,init-args
Platform: UNKNOWN
Classifier: Development Status :: 5 - Production/Stable
Classifier: License :: OSI Approved :: MIT License
Classifier: Operating System :: OS Independent
Classifier: Programming Language :: Python :: 3.8
Classifier: Programming Language :: Python :: 3.7
Classifier: Programming Language :: Python :: 3 :: Only
Requires-Python: >=3.7, <4
Provides-Extra: test
